{"nodes": [{"id": "c_users_eduardo_onedrive_documentos_site_sindicato_superpowers_sdd_task_1_brief_md", "label": "task-1-brief.md", "file_type": "document", "source_file": ".superpowers/sdd/task-1-brief.md", "source_location": "L1"}, {"id": "sdd_task_1_brief_task_1_resolu\u00e7\u00e3o_de_canal_e_busca_de_v\u00eddeos_do_youtube", "label": "Task 1: Resolu\u00e7\u00e3o De Canal E Busca De V\u00eddeos Do YouTube", "file_type": "document", "source_file": ".superpowers/sdd/task-1-brief.md", "source_location": "L1"}], "edges": [{"source": "c_users_eduardo_onedrive_documentos_site_sindicato_superpowers_sdd_task_1_brief_md", "target": "sdd_task_1_brief_task_1_resolu\u00e7\u00e3o_de_canal_e_busca_de_v\u00eddeos_do_youtube", "relation": "contains", "confidence": "EXTRACTED", "source_file": ".superpowers/sdd/task-1-brief.md", "source_location": "L1", "weight": 1.0}], "input_tokens": 0, "output_tokens": 0}