{"nodes": [{"id": "front_page_php", "label": "WordPress Front Page Template", "file_type": "code", "source_file": "wp-content/themes/sindicato/front-page.php", "source_location": null, "source_url": null, "captured_at": null, "author": null, "contributor": null}, {"id": "front_page_php", "label": "front-page.php", "file_type": "code", "source_file": "wp-content/themes/sindicato/front-page.php", "source_location": null, "source_url": null, "captured_at": null, "author": null, "contributor": null}, {"id": "front_page_php", "label": "front-page.php", "file_type": "code", "source_file": "wp-content/themes/sindicato/front-page.php", "source_location": null, "source_url": null, "captured_at": null, "author": null, "contributor": null}], "edges": [], "hyperedges": []}